bcchapi/__init__.py
bcchapi/credentials.py
bcchapi/exception.py
bcchapi/siete.py
bcchapi/webservice.py
bcchapi/wsresponse.py
bcchapi-1.1.2.dist-info/LICENSE
bcchapi-1.1.2.dist-info/METADATA
bcchapi-1.1.2.dist-info/WHEEL
bcchapi-1.1.2.dist-info/top_level.txt
bcchapi-1.1.2.dist-info/RECORD
