Metadata-Version: 2.1
Name: bcchapi
Version: 1.1.2
Summary: Python web service API for the Central Bank of Chile Statistical Database.
Author-email: Banco Central de Chile <stat@bcentral.cl>
Project-URL: Homepage, https://si3.bcentral.cl/estadisticas/Principal1/Web_Services/index.htm
Project-URL: Bug Tracker, https://contactocentral.bcentral.cl/
Classifier: Programming Language :: Python :: 3
Classifier: License :: OSI Approved :: MIT License
Classifier: Operating System :: OS Independent
Requires-Python: >=3.7
License-File: LICENSE
Requires-Dist: pandas>=1.2.0
Requires-Dist: requests>=2.0.1
